Metadata-Version: 1.1
Name: djangoplicity-mailman
Version: 0.4.1
Summary: Interface to Mailman Web-API
Home-page: https://github.com/djangoplicity/djangoplicity-mailman
Author: Bernd Schlapsi
Author-email: albert@albertoconnor.ca
License: GNU LGPL v2.1
Download-URL: https://github.com/djangoplicity/djangoplicity-mailman/archive/refs/tags/0.4.1.tar.gz
Platform: any
